legimens/App.py
legimens/Object.py
legimens/__init__.py
legimens/helpers/AttrDict.py
legimens/helpers/__init__.py
legimens/helpers/dictMap.py
legimens/websocket/__init__.py
legimens/websocket/server.py
legimens-0.2.3.dist-info/METADATA
legimens-0.2.3.dist-info/WHEEL
legimens-0.2.3.dist-info/top_level.txt
legimens-0.2.3.dist-info/RECORD
