Metadata-Version: 2.1
Name: legimens
Version: 0.2.3
Summary: UNKNOWN
Home-page: https://github.com/DaniloZZZ/legimens
Author: Danil Lykov
Author-email: lkvdan@gmail.com
License: MIT
Platform: UNKNOWN
Requires-Python: >=3.6
Requires-Dist: loguru
Requires-Dist: trio-websocket
